LICENSE
README.md
setup.py
librenv/__init__.py
librenv/__main__.py
librenv/librenv.py
librenv/project.py
librenv.egg-info/PKG-INFO
librenv.egg-info/SOURCES.txt
librenv.egg-info/dependency_links.txt
librenv.egg-info/entry_points.txt
librenv.egg-info/top_level.txt
librenv/api/__init__.py
librenv/api/character.py
librenv/api/color.py
librenv/api/drawable.py
librenv/api/image.py
librenv/api/text.py
librenv/api/vector2.py