Metadata-Version: 2.1
Name: librenv
Version: 0.1.3
Summary: Simple visual novel engine, written on Python3+SDL2.
Home-page: https://notabug.org/loliconshik3/librenv
Author: loliconshik3
License-File: LICENSE
